fiftyone_db_ubuntu1604-0.3.0.data/purelib/fiftyone/db/__init__.py
fiftyone_db_ubuntu1604-0.3.0.data/purelib/fiftyone/db/bin/mongod
fiftyone_db_ubuntu1604-0.3.0.dist-info/LICENSE
fiftyone_db_ubuntu1604-0.3.0.dist-info/METADATA
fiftyone_db_ubuntu1604-0.3.0.dist-info/WHEEL
fiftyone_db_ubuntu1604-0.3.0.dist-info/top_level.txt
fiftyone_db_ubuntu1604-0.3.0.dist-info/RECORD
